healthy_sanjid/__init__.py
healthy_sanjid/main.py
healthy_sanjid-0.2.2.dist-info/METADATA
healthy_sanjid-0.2.2.dist-info/WHEEL
healthy_sanjid-0.2.2.dist-info/top_level.txt
healthy_sanjid-0.2.2.dist-info/RECORD
