Metadata-Version: 2.1
Name: healthy_sanjid
Version: 0.2.2
Requires-Dist: requests
